README.rst
setup.py
metafs/__init__.py
metafs/metafs.py
metafs/peparser.py
metafs.egg-info/PKG-INFO
metafs.egg-info/SOURCES.txt
metafs.egg-info/dependency_links.txt
metafs.egg-info/requires.txt
metafs.egg-info/top_level.txt