Metadata-Version: 1.1
Name: metafs
Version: 0.0.14
Summary: MetaFS is for generating a datastore of file metadata for rapid complex searches
Home-page: http://github.com/yahoo/metafs
Author: Sean Gillespie
Author-email: seagill@yahoo-inc.com
License: LICENSE.txt
Platform: UNKNOWN
Classifier: License :: OSI Approved :: BSD License
Classifier: Operating System :: POSIX :: Linux
Classifier: Programming Language :: Python
